hypertunity/__init__.py
hypertunity/domain.py
hypertunity/trial.py
hypertunity/utils.py
hypertunity/optimisation/__init__.py
hypertunity/optimisation/base.py
hypertunity/optimisation/bo.py
hypertunity/optimisation/exhaustive.py
hypertunity/optimisation/random.py
hypertunity/reports/__init__.py
hypertunity/reports/base.py
hypertunity/reports/table.py
hypertunity/reports/tensorboard.py
hypertunity/scheduling/__init__.py
hypertunity/scheduling/jobs.py
hypertunity/scheduling/scheduler.py
hypertunity-1.0.1.dist-info/LICENSE
hypertunity-1.0.1.dist-info/METADATA
hypertunity-1.0.1.dist-info/WHEEL
hypertunity-1.0.1.dist-info/top_level.txt
hypertunity-1.0.1.dist-info/RECORD
