Metadata-Version: 2.1
Name: hypertunity
Version: 1.0.1
Summary: A toolset for distributed black-box hyperparameter optimisation.
Home-page: https://github.com/gdikov/hypertunity
Author: Georgi Dikov
Author-email: gvdikov@gmail.com
License: UNKNOWN
Platform: UNKNOWN
Classifier: Development Status :: 5 - Production/Stable
Classifier: Intended Audience :: Developers
Classifier: Intended Audience :: Education
Classifier: Intended Audience :: Science/Research
Classifier: License :: OSI Approved :: Apache Software License
Classifier: Programming Language :: Python :: 3.6
Classifier: Programming Language :: Python :: 3.7
Classifier: Programming Language :: Python :: 3.8
Classifier: Topic :: Software Development :: Libraries
Classifier: Topic :: Software Development :: Libraries :: Python Modules
Requires-Python: >=3.6
Requires-Dist: beautifultable (>=0.7.0)
Requires-Dist: gpy (>=1.9.8)
Requires-Dist: gpyopt (==1.2.5)
Requires-Dist: joblib (>=0.13.2)
Requires-Dist: matplotlib (>=3.0)
Requires-Dist: numpy (>=1.16)
Requires-Dist: tinydb (>=3.13.0)
Requires-Dist: dataclasses ; python_version < "3.7"
Provides-Extra: docs
Requires-Dist: sphinx (>=2.2.0) ; extra == 'docs'
Requires-Dist: sphinx-rtd-theme (>=0.4.3) ; extra == 'docs'
Provides-Extra: tensorboard
Requires-Dist: tensorflow (>=1.14.0) ; extra == 'tensorboard'
Requires-Dist: tensorboard (>=1.14.0) ; extra == 'tensorboard'
Provides-Extra: tests
Requires-Dist: pytest (>=4.6.3) ; extra == 'tests'
Requires-Dist: pytest-timeout (>=1.3.3) ; extra == 'tests'
